parsimonious-stubs/METADATA.toml
parsimonious-stubs/__init__.pyi
parsimonious-stubs/exceptions.pyi
parsimonious-stubs/expressions.pyi
parsimonious-stubs/grammar.pyi
parsimonious-stubs/nodes.pyi
parsimonious-stubs/py.typed
parsimonious-stubs/utils.pyi
types_parsimonious-0.10.0.20250822.dist-info/licenses/LICENSE
types_parsimonious-0.10.0.20250822.dist-info/METADATA
types_parsimonious-0.10.0.20250822.dist-info/WHEEL
types_parsimonious-0.10.0.20250822.dist-info/top_level.txt
types_parsimonious-0.10.0.20250822.dist-info/RECORD
